pyminhaufop/__init__.py
pyminhaufop/minha_ufop.py
pyminhaufop/exceptions/MinhaUFOPGenericError.py
pyminhaufop/exceptions/MinhaUFOPHTTPError.py
pyminhaufop/exceptions/__init__.py
pyminhaufop-0.3.1.dist-info/LICENSE
pyminhaufop-0.3.1.dist-info/METADATA
pyminhaufop-0.3.1.dist-info/WHEEL
pyminhaufop-0.3.1.dist-info/top_level.txt
pyminhaufop-0.3.1.dist-info/RECORD
