Metadata-Version: 2.1
Name: pyminhaufop
Version: 0.3.1
Summary: Wrapper não-oficial para a API mobile da MinhaUFOP
Home-page: https://github.com/eitchtee/pyMinhaUFOP
Author: Herculino Trotta Neto
Author-email: herculinotrotta@gmail.com
License: MIT
Keywords: UFOP,api,wrapper
Platform: UNKNOWN
Classifier: Programming Language :: Python :: 3
Classifier: License :: OSI Approved :: MIT License
Classifier: Operating System :: OS Independent
Requires-Python: >=3.6
Requires-Dist: requests
